sourced_ml-0.8.2-py3.5-nspkg.pth
sourced/ml/__init__.py
sourced/ml/__main__.py
sourced/ml/modelforgecfg.py
sourced/ml/algorithms/__init__.py
sourced/ml/algorithms/id_embedding.py
sourced/ml/algorithms/swivel.py
sourced/ml/algorithms/tf_idf.py
sourced/ml/algorithms/token_parser.py
sourced/ml/algorithms/uast_id_distance.py
sourced/ml/algorithms/uast_ids_to_bag.py
sourced/ml/algorithms/uast_inttypes_to_graphlets.py
sourced/ml/algorithms/uast_inttypes_to_nodes.py
sourced/ml/algorithms/uast_struct_to_bag.py
sourced/ml/algorithms/uast_to_bag.py
sourced/ml/algorithms/uast_to_id_sequence.py
sourced/ml/algorithms/uast_to_role_id_pairs.py
sourced/ml/algorithms/id_splitter/README.md
sourced/ml/algorithms/id_splitter/__init__.py
sourced/ml/algorithms/id_splitter/features.py
sourced/ml/algorithms/id_splitter/nn_model.py
sourced/ml/algorithms/id_splitter/pipeline.py
sourced/ml/cmd/__init__.py
sourced/ml/cmd/args.py
sourced/ml/cmd/bigartm2asdf.py
sourced/ml/cmd/bow_converters.py
sourced/ml/cmd/id2role_eval.py
sourced/ml/cmd/id2vec_postprocess.py
sourced/ml/cmd/id2vec_preprocess.py
sourced/ml/cmd/id2vec_project.py
sourced/ml/cmd/merge_bow.py
sourced/ml/cmd/merge_coocc.py
sourced/ml/cmd/merge_df.py
sourced/ml/cmd/preprocess_repos.py
sourced/ml/cmd/repos2bow.py
sourced/ml/cmd/repos2coocc.py
sourced/ml/cmd/repos2df.py
sourced/ml/cmd/repos2id_distance.py
sourced/ml/cmd/repos2id_sequence.py
sourced/ml/cmd/repos2ids.py
sourced/ml/cmd/repos2roles_and_ids.py
sourced/ml/cmd/run_swivel.py
sourced/ml/cmd/train_id_split.py
sourced/ml/extractors/__init__.py
sourced/ml/extractors/bags_extractor.py
sourced/ml/extractors/children.py
sourced/ml/extractors/graphlets.py
sourced/ml/extractors/helpers.py
sourced/ml/extractors/id_sequence.py
sourced/ml/extractors/identifier_distance.py
sourced/ml/extractors/identifiers.py
sourced/ml/extractors/literals.py
sourced/ml/extractors/uast_random_walk.py
sourced/ml/extractors/uast_seq.py
sourced/ml/models/__init__.py
sourced/ml/models/bow.py
sourced_ml-0.8.2.dist-info/METADATA
sourced_ml-0.8.2.dist-info/WHEEL
sourced_ml-0.8.2.dist-info/entry_points.txt
sourced_ml-0.8.2.dist-info/namespace_packages.txt
sourced_ml-0.8.2.dist-info/top_level.txt
sourced_ml-0.8.2.dist-info/RECORD
