Metadata-Version: 2.1
Name: sourced-ml
Version: 0.8.2
Summary: Framework for machine learning on source code. Provides API and tools to train and use models based on source code features extracted from Babelfish's UASTs.
Home-page: https://github.com/src-d/ml
Author: source{d}
Author-email: machine-learning@sourced.tech
License: Apache 2.0
Download-URL: https://github.com/src-d/ml
Keywords: machine learning on source code,word2vec,id2vec,github,swivel,bow,bblfsh,babelfish
Platform: UNKNOWN
Classifier: Development Status :: 3 - Alpha
Classifier: Environment :: Console
Classifier: Intended Audience :: Developers
Classifier: License :: OSI Approved :: Apache Software License
Classifier: Operating System :: POSIX
Classifier: Programming Language :: Python :: 3.5
Classifier: Programming Language :: Python :: 3.6
Classifier: Programming Language :: Python :: 3.7
Classifier: Topic :: Software Development :: Libraries
Requires-Python: >=3.4
Requires-Dist: PyStemmer (<2.0,>=1.3)
Requires-Dist: bblfsh (<3.0,>=2.2.1)
Requires-Dist: modelforge (<0.12,>=0.11.1)
Requires-Dist: sourced-jgit-spark-connector (<2.1.0,>=2.0.1)
Requires-Dist: humanize (<0.6,>=0.5.0)
Requires-Dist: parquet (<2.0,>=1.2)
Requires-Dist: pygments (<3.0,>=2.2.0)
Requires-Dist: keras (<3.0,>=2.0)
Requires-Dist: scikit-learn (<1.0,>=0.19)
Requires-Dist: tqdm (<5.0,>=4.20)
Requires-Dist: typing ; python_version < "3.5"
Provides-Extra: pandas
Requires-Dist: pandas (<1.0,>=0.24.1) ; extra == 'pandas'
Provides-Extra: tf
Requires-Dist: tensorflow (<2.0,>=1.0) ; extra == 'tf'
Provides-Extra: tf_gpu
Requires-Dist: tensorflow-gpu (<2.0,>=1.0) ; extra == 'tf_gpu'
